linux_joystick/__init__.py
linux_joystick/joystick.py
linux_joystick_py-0.0.4.dist-info/LICENSE
linux_joystick_py-0.0.4.dist-info/METADATA
linux_joystick_py-0.0.4.dist-info/WHEEL
linux_joystick_py-0.0.4.dist-info/top_level.txt
linux_joystick_py-0.0.4.dist-info/RECORD
